docs/conf.py
gitops_configserver/__init__.py
gitops_configserver/cli.py
gitops_configserver/config.py
gitops_configserver/config_loader.py
gitops_configserver/extensions.py
gitops_configserver/git.py
gitops_configserver/hieradata_resolver.py
gitops_configserver/server.py
gitops_configserver/templates_rendering.py
gitops_configserver/utils.py
gitops_configserver/workflow.py
gitops_configserver/configs/__init__.py
gitops_configserver/configs/views.py
gitops_configserver-1.4.20250413150319.dist-info/licenses/LICENSE
tests/__init__.py
tests/test_hieradata_resolver.py
tests/test_rendering.py
tests/test_template_rendering_handler.py
tests/test_variables_resolver.py
gitops_configserver-1.4.20250413150319.dist-info/METADATA
gitops_configserver-1.4.20250413150319.dist-info/WHEEL
gitops_configserver-1.4.20250413150319.dist-info/entry_points.txt
gitops_configserver-1.4.20250413150319.dist-info/top_level.txt
gitops_configserver-1.4.20250413150319.dist-info/RECORD
