Metadata-Version: 2.4
Name: gitops-configserver
Version: 1.4.20250413150319
Author-email: Piotr Przetacznik <piotr.przetacznik+gitops@gmail.com>
License: All rights reserved by Piotr Przetacznik.
Classifier: Programming Language :: Python :: 3.12
Classifier: Programming Language :: Python :: 3.13
License-File: LICENSE
Requires-Dist: pytest
Requires-Dist: Jinja2
Requires-Dist: pyyaml
Requires-Dist: Flask
Requires-Dist: flask-restful
Requires-Dist: Sphinx
Requires-Dist: sphinx_rtd_theme
Dynamic: license-file
